{
  "An": "Lê Thị Trường An",
  "Bảo Trâm": "Nguyễn Thị Bảo Trâm",
  "Bảo Trân": "VÕ, Ngọc Bảo Trân",
  "Diễm Hồng": "Nguyễn Thị Diễm Hồng",
  "Diễm My": "Trần Hà Diễm My",
  "Gia Mẫn": "Trần Thanh Gia Mẫn",
  "Hoàng Yến": "Quan Hoàng Yến",
  "Huỳnh Anh": "Huỳnh Anh",
  "Hương Ly": "Hương Ly",
  "Hồng Hạnh": "Nguyễn Thị Hồng Hạnh",
  "Khiết Oanh": "Trần Khiết Oanh",
  "Khánh Linh": "khánh linh",
  "Kim Dung": "Nguyễn Thị Kim Dung",
  "Lan Anh": "Nguyễn Thị Lan Anh",
  "Lâm Hà": "Lâm Hà",
  "Lê Hoàng": "Lê Hoàng",
  "Lợi": "Phạm Thị Lợi",
  "Mạc Đan": "Trương Thị Mạc Đan",
  "Mỹ Ly": "Nguyễn Thị Mỹ Ly",
  "Mỹ Vi": "Võ Mỹ Vi",
  "Ngọc Hà": "Nguyễn Ngọc Hà",
  "Ngọc Hà/Phạm Lợi": "__SHARED:Nguyễn Ngọc Hà|Phạm Thị Lợi__",
  "Ngọc Hân": "Nguyễn Ngọc Hân",
  "Ngọc Hạ": "Nguyễn Ngọc Hà",
  "Ngọc Sơn": "Đào Ngọc Sơn",
  "Ngọc Vy": "Ngọc Vy",
  "Phan Thảnh": "Phan Thị Thảnh",
  "Phúc Lâm": "Nguyễn Phúc Lâm",
  "Phương Thảo": "Phạm Thị Ngọc Thảo",
  "Phạm Lợi": "Phạm Thị Lợi",
  "Thành Vinh": "Nguyễn Thành Vinh",
  "Thúy An": "NGUYEN Hoang Thuy An",
  "Thế Hiền": "Nguyễn Thế Hiền",
  "Thục Nhi": "Lê Bá Thục Nhi",
  "Thủy Chung": "Nguyễn Tấn Thủy Chung",
  "Trúc Quỳnh": "Đoàn Ngọc Trúc Quỳnh",
  "Tất Thành": "La Tất Thành",
  "Uyên Phương": "Hoàng Trần Uyên Phương",
  "Vũ Hòa": "Vũ Thị Hòa"
}